{
  "_class": "group",
  "do_objectID": "EE25F4DB-B40A-47E0-B24B-4EFF17863D74",
  "exportOptions": {
    "_class": "exportOptions",
    "exportFormats": [
    ],
    "includedLayerIds": [
    ],
    "layerOptions": 0,
    "shouldTrim": false
  },
  "frame": {
    "_class": "rect",
    "constrainProportions": false,
    "height": 47,
    "width": 300,
    "x": 393,
    "y": 114
  },
  "hasClickThrough": false,
  "isFlippedHorizontal": false,
  "isFlippedVertical": false,
  "isLocked": false,
  "isVisible": true,
  "layerListExpandedType": 0,
  "layers": [
    {
      "class": "text",
      "id": "039FD7BD-66A2-4421-A470-FD30A9C04D9D"
    },
    {
      "class": "shapeGroup",
      "id": "CC1B9BF9-9C13-44D0-B3C4-3FA443AC1FC2"
    }
  ],
  "name": "第三方订单号",
  "nameIsFixed": true,
  "resizingConstraint": 63,
  "resizingType": 0,
  "rotation": 0,
  "shouldBreakMaskChain": false,
  "style": {
    "_class": "style",
    "endDecorationType": 0,
    "miterLimit": 10,
    "startDecorationType": 0
  }
}