{
  "_class": "artboard",
  "backgroundColor": {
    "_class": "color",
    "alpha": 1,
    "blue": 0.9882352941176471,
    "green": 0.984313725490196,
    "red": 0.9803921568627451
  },
  "do_objectID": "ECE9A5EB-36FF-4C33-9FA7-CB8A25C40329",
  "exportOptions": {
    "_class": "exportOptions",
    "exportFormats": [
      {
        "_class": "exportFormat",
        "absoluteSize": 0,
        "fileFormat": "jpg",
        "name": "",
        "namingScheme": 0,
        "scale": 2,
        "visibleScaleType": 0
      }
    ],
    "includedLayerIds": [
    ],
    "layerOptions": 0,
    "shouldTrim": false
  },
  "frame": {
    "_class": "rect",
    "constrainProportions": false,
    "height": 960,
    "width": 1366,
    "x": -418,
    "y": -301
  },
  "grid": {
    "_class": "simpleGrid",
    "gridSize": 20,
    "isEnabled": false,
    "thickGridTimes": 10
  },
  "hasBackgroundColor": true,
  "hasClickThrough": true,
  "horizontalRulerData": {
    "_class": "rulerData",
    "base": -695,
    "guides": [
      4615
    ]
  },
  "includeBackgroundColorInExport": true,
  "includeInCloudUpload": true,
  "isFlippedHorizontal": false,
  "isFlippedVertical": false,
  "isLocked": false,
  "isVisible": true,
  "layerListExpandedType": 2,
  "layers": [
    {
      "class": "group",
      "id": "50134611-A633-4056-BF20-D29F61FADBFF"
    },
    {
      "class": "group",
      "id": "C731ED1C-832E-4CCA-BFCE-19CC3E843208"
    },
    {
      "class": "group",
      "id": "32D8E35A-0A3D-4B58-8A0E-E1FB88D38A10"
    },
    {
      "class": "group",
      "id": "C079CAF7-6C08-41D1-B868-BB02F2E3F741"
    },
    {
      "class": "group",
      "id": "F7706512-8ADF-452B-94EE-BE7BCCF55137"
    },
    {
      "class": "group",
      "id": "0A2C68C1-860C-4438-86EE-6F12479DB3BF"
    }
  ],
  "layout": {
    "_class": "layoutGrid",
    "columnWidth": 68,
    "drawHorizontal": false,
    "drawHorizontalLines": false,
    "drawVertical": true,
    "gutterHeight": 12,
    "gutterWidth": 29.5,
    "guttersOutside": true,
    "horizontalOffset": 135,
    "isEnabled": false,
    "numberOfColumns": 12,
    "rowHeightMultiplication": 5,
    "totalWidth": 1170
  },
  "name": "APP版本管理",
  "nameIsFixed": true,
  "resizesContent": false,
  "resizingConstraint": 63,
  "resizingType": 0,
  "rotation": 0,
  "shouldBreakMaskChain": false,
  "style": {
    "_class": "style",
    "endDecorationType": 0,
    "fills": [
      {
        "_class": "fill",
        "color": {
          "_class": "color",
          "alpha": 1,
          "blue": 1,
          "green": 1,
          "red": 1
        },
        "fillType": 0,
        "isEnabled": true,
        "noiseIndex": 0,
        "noiseIntensity": 0,
        "patternFillType": 1,
        "patternTileScale": 1
      }
    ],
    "miterLimit": 10,
    "startDecorationType": 0
  },
  "userInfo": {
    "com.animaapp.stc-sketch-plugin": {
      "kModelPropertiesKey": {
      }
    }
  },
  "verticalRulerData": {
    "_class": "rulerData",
    "base": -91,
    "guides": [
    ]
  }
}