{
  "_class": "group",
  "do_objectID": "CB909D20-C5B1-4E93-AFED-382B7AD9C14D",
  "exportOptions": {
    "_class": "exportOptions",
    "exportFormats": [
    ],
    "includedLayerIds": [
    ],
    "layerOptions": 0,
    "shouldTrim": false
  },
  "frame": {
    "_class": "rect",
    "constrainProportions": false,
    "height": 1345,
    "width": 200,
    "x": 0,
    "y": 0
  },
  "hasClickThrough": false,
  "isFlippedHorizontal": false,
  "isFlippedVertical": false,
  "isLocked": false,
  "isVisible": true,
  "layerListExpandedType": 2,
  "layers": [
    {
      "class": "shapeGroup",
      "id": "7C97AFA1-FAA1-4773-8945-8E7EA1E59F1C"
    },
    {
      "class": "group",
      "id": "1341C498-7BFB-47C6-B861-926728850360"
    },
    {
      "class": "shapeGroup",
      "id": "5DC9DBE6-EF35-4F98-BA3E-49A484C143DC"
    },
    {
      "class": "group",
      "id": "AA0410EE-29B8-4D1B-9048-6411B356B3AB"
    },
    {
      "class": "group",
      "id": "4149678E-C0E7-4C61-9A3E-3AB4EF064B0D"
    },
    {
      "class": "group",
      "id": "FDB4C5AE-4E2F-494D-AE26-8151B978685B"
    },
    {
      "class": "group",
      "id": "229D0D3C-27C2-4CCE-861B-2A8CF4EA316B"
    },
    {
      "class": "group",
      "id": "CDD1C043-0522-46C8-BA86-D41C6580B088"
    },
    {
      "class": "group",
      "id": "0945A1AD-99F7-4944-9852-4F146FEC2D9E"
    },
    {
      "class": "group",
      "id": "886418E3-8FC3-4B5F-8064-78BA7FB16C36"
    },
    {
      "class": "group",
      "id": "FA9A00F5-88EF-4D40-994C-5830E9DD4CC3"
    },
    {
      "class": "group",
      "id": "DFD4E00C-7C33-4648-9879-3AEE4F26A58E"
    },
    {
      "class": "group",
      "id": "06311D8A-988A-4835-914F-79516BE6322B"
    },
    {
      "class": "group",
      "id": "D4775AE2-B2B9-42E7-AEDF-3E8616288573"
    }
  ],
  "name": "侧边栏",
  "nameIsFixed": false,
  "resizingConstraint": 63,
  "resizingType": 0,
  "rotation": 0,
  "shouldBreakMaskChain": false,
  "style": {
    "_class": "style",
    "endDecorationType": 0,
    "miterLimit": 10,
    "startDecorationType": 0
  }
}