{
  "_class": "group",
  "do_objectID": "75F7D206-AC12-45D4-A6CF-A58F4D3B336C",
  "exportOptions": {
    "_class": "exportOptions",
    "exportFormats": [
    ],
    "includedLayerIds": [
    ],
    "layerOptions": 0,
    "shouldTrim": false
  },
  "frame": {
    "_class": "rect",
    "constrainProportions": false,
    "height": 317,
    "width": 1126,
    "x": 220,
    "y": 106
  },
  "hasClickThrough": false,
  "isFlippedHorizontal": false,
  "isFlippedVertical": false,
  "isLocked": false,
  "isVisible": true,
  "layerListExpandedType": 2,
  "layers": [
    {
      "class": "shapeGroup",
      "id": "E706EB3C-EFD3-45F0-B80F-0BC2BE10DED4"
    },
    {
      "class": "group",
      "id": "EA512940-0A93-4E46-98F0-749FF8334621"
    },
    {
      "class": "group",
      "id": "9668DCA2-3877-437D-8A8C-6177DE0BAD8B"
    },
    {
      "class": "text",
      "id": "DEDE9031-3DC3-456A-B0D5-08368A286800"
    }
  ],
  "name": "Group 2 Copy",
  "nameIsFixed": false,
  "resizingConstraint": 63,
  "resizingType": 0,
  "rotation": 0,
  "shouldBreakMaskChain": false,
  "style": {
    "_class": "style",
    "endDecorationType": 0,
    "miterLimit": 10,
    "startDecorationType": 0
  }
}