{
  "_class": "group",
  "do_objectID": "6A6A3258-E7EB-4CBF-A57F-D5BAEEE9150F",
  "exportOptions": {
    "_class": "exportOptions",
    "exportFormats": [
    ],
    "includedLayerIds": [
    ],
    "layerOptions": 0,
    "shouldTrim": false
  },
  "frame": {
    "_class": "rect",
    "constrainProportions": false,
    "height": 30,
    "width": 80,
    "x": 30,
    "y": 287
  },
  "hasClickThrough": false,
  "isFlippedHorizontal": false,
  "isFlippedVertical": false,
  "isLocked": false,
  "isVisible": true,
  "layerListExpandedType": 0,
  "layers": [
    {
      "class": "shapeGroup",
      "id": "CB875818-2D0D-4090-97C3-772D63324E6E"
    },
    {
      "class": "text",
      "id": "4CA2E615-DFB2-438D-AD7E-CE9CDD2A1C88"
    }
  ],
  "name": "保存",
  "nameIsFixed": true,
  "resizingConstraint": 63,
  "resizingType": 0,
  "rotation": 0,
  "shouldBreakMaskChain": false,
  "style": {
    "_class": "style",
    "endDecorationType": 0,
    "miterLimit": 10,
    "startDecorationType": 0
  }
}