{
  "_class": "symbolInstance",
  "do_objectID": "6F8CB0AC-A121-4C24-85E4-6FF1D3008A37",
  "exportOptions": {
    "_class": "exportOptions",
    "exportFormats": [
    ],
    "includedLayerIds": [
    ],
    "layerOptions": 0,
    "shouldTrim": false
  },
  "frame": {
    "_class": "rect",
    "constrainProportions": false,
    "height": 24,
    "width": 60,
    "x": 945,
    "y": 14
  },
  "horizontalSpacing": 0,
  "isFlippedHorizontal": false,
  "isFlippedVertical": false,
  "isLocked": false,
  "isVisible": true,
  "layerListExpandedType": 0,
  "masterInfluenceEdgeMaxXPadding": 0,
  "masterInfluenceEdgeMaxYPadding": 0,
  "masterInfluenceEdgeMinXPadding": 0,
  "masterInfluenceEdgeMinYPadding": 0,
  "name": "删除 copy 2",
  "nameIsFixed": false,
  "resizingConstraint": 63,
  "resizingType": 0,
  "rotation": 0,
  "shouldBreakMaskChain": false,
  "style": {
    "_class": "style",
    "endDecorationType": 0,
    "miterLimit": 10,
    "startDecorationType": 0
  },
  "symbolID": "F6469A76-8523-4FAA-9BA4-7E701574EEA2",
  "verticalSpacing": 0
}