{
  "_class": "group",
  "do_objectID": "BE59F902-3270-4E53-94F3-A87AC83D4F6E",
  "exportOptions": {
    "_class": "exportOptions",
    "exportFormats": [
    ],
    "includedLayerIds": [
    ],
    "layerOptions": 0,
    "shouldTrim": false
  },
  "frame": {
    "_class": "rect",
    "constrainProportions": false,
    "height": 40,
    "width": 200,
    "x": 0,
    "y": 410
  },
  "hasClickThrough": false,
  "isFlippedHorizontal": false,
  "isFlippedVertical": false,
  "isLocked": false,
  "isVisible": true,
  "layerListExpandedType": 0,
  "layers": [
    {
      "class": "shapeGroup",
      "id": "29D12518-53A2-45B5-9CF9-7B1D3687D1A5"
    },
    {
      "class": "text",
      "id": "9B7ACE32-208B-4B08-B0D8-A66B5B679D7A"
    },
    {
      "class": "bitmap",
      "id": "8E79BF02-5EE0-46D4-8CFC-94F3730C1A2D"
    },
    {
      "class": "bitmap",
      "id": "967E77CC-B46B-40FF-B31D-9492B3CD312B"
    }
  ],
  "name": "JD",
  "nameIsFixed": true,
  "resizingConstraint": 63,
  "resizingType": 0,
  "rotation": 0,
  "shouldBreakMaskChain": false,
  "style": {
    "_class": "style",
    "endDecorationType": 0,
    "miterLimit": 10,
    "startDecorationType": 0
  }
}