{
  "_class": "group",
  "do_objectID": "A720F785-D9A6-4EFB-889A-A20629DFBEAE",
  "exportOptions": {
    "_class": "exportOptions",
    "exportFormats": [
    ],
    "includedLayerIds": [
    ],
    "layerOptions": 0,
    "shouldTrim": false
  },
  "frame": {
    "_class": "rect",
    "constrainProportions": false,
    "height": 30,
    "width": 367,
    "x": 30,
    "y": 197
  },
  "hasClickThrough": false,
  "isFlippedHorizontal": false,
  "isFlippedVertical": false,
  "isLocked": false,
  "isVisible": true,
  "layerListExpandedType": 2,
  "layers": [
    {
      "class": "shapeGroup",
      "id": "26C1BC2A-7554-4DD4-8F48-7DE6DC69D16D"
    },
    {
      "class": "text",
      "id": "FC1ADF0F-79BB-4B35-9345-25B422972676"
    }
  ],
  "name": "详细地址 copy 3",
  "nameIsFixed": true,
  "resizingConstraint": 63,
  "resizingType": 0,
  "rotation": 0,
  "shouldBreakMaskChain": false,
  "style": {
    "_class": "style",
    "endDecorationType": 0,
    "miterLimit": 10,
    "startDecorationType": 0
  }
}