{
  "_class": "group",
  "do_objectID": "3FF0BC90-1A87-4646-864E-4C3510FDBA56",
  "exportOptions": {
    "_class": "exportOptions",
    "exportFormats": [
    ],
    "includedLayerIds": [
    ],
    "layerOptions": 0,
    "shouldTrim": false
  },
  "frame": {
    "_class": "rect",
    "constrainProportions": false,
    "height": 47,
    "width": 300,
    "x": 786,
    "y": 57
  },
  "hasClickThrough": false,
  "isFlippedHorizontal": false,
  "isFlippedVertical": false,
  "isLocked": false,
  "isVisible": true,
  "layerListExpandedType": 0,
  "layers": [
    {
      "class": "group",
      "id": "8233E089-B4B0-44CA-85C5-45B225FE5E66"
    },
    {
      "class": "shapeGroup",
      "id": "1BEAC705-8115-49D6-983C-CA65A7ABD33B"
    },
    {
      "class": "bitmap",
      "id": "507D4D43-BB06-4A3C-BFA5-33F7942F9C83"
    },
    {
      "class": "shapeGroup",
      "id": "32D26FCB-FC10-4FCB-916C-DC4FCE533BA0"
    },
    {
      "class": "bitmap",
      "id": "1270669A-A7BB-4F01-AC47-9A9F7D751B3F"
    },
    {
      "class": "text",
      "id": "2C6249FD-534C-4556-B446-C29F57A4F6C5"
    },
    {
      "class": "text",
      "id": "E64206AD-C5BD-4465-A364-2425315BCEA1"
    },
    {
      "class": "text",
      "id": "38CC1E74-40FB-4434-AE59-C2A1D26665C6"
    }
  ],
  "name": "库存区间",
  "nameIsFixed": true,
  "resizingConstraint": 63,
  "resizingType": 0,
  "rotation": 0,
  "shouldBreakMaskChain": false,
  "style": {
    "_class": "style",
    "endDecorationType": 0,
    "miterLimit": 10,
    "startDecorationType": 0
  }
}